example/__init__.py
example/example.py
pygltr/__init__.py
pygltr/pygltr.py
pygltr-0.8.0.dist-info/DESCRIPTION.rst
pygltr-0.8.0.dist-info/METADATA
pygltr-0.8.0.dist-info/RECORD
pygltr-0.8.0.dist-info/WHEEL
pygltr-0.8.0.dist-info/metadata.json
pygltr-0.8.0.dist-info/top_level.txt
