Metadata-Version: 2.0
Name: pygltr
Version: 0.8.0
Summary: Python script to get GitLab Time Reports
Home-page: https://github.com/murthy10/pygltr
Author: Samuel Kurath
Author-email: samuel.kurath@gmail.com
License: MIT
Platform: UNKNOWN
